odoo/addons/base_phone_rate/__init__.py
odoo/addons/base_phone_rate/__manifest__.py
odoo/addons/base_phone_rate/data/decimal_precision.xml
odoo/addons/base_phone_rate/i18n/base_phone_rate.pot
odoo/addons/base_phone_rate/models/__init__.py
odoo/addons/base_phone_rate/models/phone_rate.py
odoo/addons/base_phone_rate/models/product_product.py
odoo/addons/base_phone_rate/security/ir.model.access.csv
odoo/addons/base_phone_rate/static/description/icon.png
odoo/addons/base_phone_rate/static/description/index.html
odoo/addons/base_phone_rate/views/phone_rate.xml
odoo/addons/base_phone_rate/views/product_product.xml
odoo12_addon_base_phone_rate-12.0.0.1.0.99.dev7.dist-info/METADATA
odoo12_addon_base_phone_rate-12.0.0.1.0.99.dev7.dist-info/WHEEL
odoo12_addon_base_phone_rate-12.0.0.1.0.99.dev7.dist-info/top_level.txt
odoo12_addon_base_phone_rate-12.0.0.1.0.99.dev7.dist-info/RECORD
